{"supplier":"aubrey lee & co","totalAmount":9089,"nTransactions":8,"expensesByArea":[{"name":"adult social care","value":8139},{"name":"corporate services","value":950}],"expensesByType":[{"name":"rents","value":5049},{"name":"professional fees","value":2240},{"name":"proffesional fees","value":950},{"name":"consumable items eg toilet rolls, soap etc","value":850}],"lastTransactions":[{"year":2020,"serviceArea":"adult social care","expensesType":"rents","supplier":"aubrey lee & co","amount":1250,"month":10,"paymentDate":1603065600000},{"year":2020,"serviceArea":"adult social care","expensesType":"consumable items eg toilet rolls, soap etc","supplier":"aubrey lee & co","amount":850,"month":2,"paymentDate":1581292800000},{"year":2018,"serviceArea":"adult social care","expensesType":"rents","supplier":"aubrey lee & co","amount":1350,"month":11,"paymentDate":1543449600000},{"year":2018,"serviceArea":"adult social care","expensesType":"rents","supplier":"aubrey lee & co","amount":545,"month":7,"paymentDate":1531267200000},{"year":2017,"serviceArea":"adult social care","expensesType":"professional fees","supplier":"aubrey lee & co","amount":2240,"month":11,"paymentDate":1511740800000}]}