{"supplier":"bluegroup international ltd","totalAmount":85222.94,"nTransactions":58,"expensesByArea":[{"name":"chief executives","value":85222.93999999997}],"expensesByType":[{"name":"agency staff provision","value":85222.93999999997}],"lastTransactions":[{"year":2012,"serviceArea":"chief executives","expensesType":"agency staff provision","supplier":"bluegroup international ltd","amount":768.6,"month":2,"paymentDate":1330387200000},{"year":2012,"serviceArea":"chief executives","expensesType":"agency staff provision","supplier":"bluegroup international ltd","amount":807.03,"month":2,"paymentDate":1328832000000},{"year":2012,"serviceArea":"chief executives","expensesType":"agency staff provision","supplier":"bluegroup international ltd","amount":960.75,"month":2,"paymentDate":1328486400000},{"year":2012,"serviceArea":"chief executives","expensesType":"agency staff provision","supplier":"bluegroup international ltd","amount":768.6,"month":1,"paymentDate":1327536000000},{"year":2012,"serviceArea":"chief executives","expensesType":"agency staff provision","supplier":"bluegroup international ltd","amount":576.45,"month":1,"paymentDate":1327276800000}]}