{"supplier":"bridge","totalAmount":165500,"nTransactions":12,"expensesByArea":[{"name":"manchester leisure","value":164000},{"name":"regeneration finance","value":1500}],"expensesByType":[{"name":"special events","value":139000},{"name":"professional fees","value":25000},{"name":"external repairs and maintenance for buildings","value":1000},{"name":"security","value":500}],"lastTransactions":[{"year":2021,"serviceArea":"regeneration finance","expensesType":"external repairs and maintenance for buildings","supplier":"bridge","amount":500,"month":1,"paymentDate":1610064000000},{"year":2021,"serviceArea":"regeneration finance","expensesType":"external repairs and maintenance for buildings","supplier":"bridge","amount":500,"month":1,"paymentDate":1610064000000},{"year":2020,"serviceArea":"manchester leisure","expensesType":"special events","supplier":"bridge","amount":25000,"month":1,"paymentDate":1578873600000},{"year":2019,"serviceArea":"manchester leisure","expensesType":"special events","supplier":"bridge","amount":15000,"month":11,"paymentDate":1574899200000},{"year":2019,"serviceArea":"regeneration finance","expensesType":"security","supplier":"bridge","amount":500,"month":11,"paymentDate":1574640000000}]}