{"supplier":"britannia hotels pcard only","totalAmount":148057,"nTransactions":178,"expensesByArea":[{"name":"adult social care","value":146819},{"name":"childrens & education services","value":1238}],"expensesByType":[{"name":"consumable items eg toilet rolls, soap etc","value":120063},{"name":"payments for services","value":15291},{"name":"subsistence and conference expenses","value":8082},{"name":"bed and breakfast accommodation expenditure","value":2640},{"name":"personal needs of client","value":1238}],"lastTransactions":[{"year":2021,"serviceArea":"adult social care","expensesType":"consumable items eg toilet rolls, soap etc","supplier":"britannia hotels pcard only","amount":956,"month":12,"paymentDate":1639612800000},{"year":2021,"serviceArea":"adult social care","expensesType":"consumable items eg toilet rolls, soap etc","supplier":"britannia hotels pcard only","amount":926,"month":12,"paymentDate":1639612800000},{"year":2021,"serviceArea":"adult social care","expensesType":"consumable items eg toilet rolls, soap etc","supplier":"britannia hotels pcard only","amount":915,"month":12,"paymentDate":1639612800000},{"year":2021,"serviceArea":"adult social care","expensesType":"consumable items eg toilet rolls, soap etc","supplier":"britannia hotels pcard only","amount":746,"month":12,"paymentDate":1639612800000},{"year":2021,"serviceArea":"adult social care","expensesType":"consumable items eg toilet rolls, soap etc","supplier":"britannia hotels pcard only","amount":735,"month":12,"paymentDate":1639612800000}]}