{"supplier":"bt featurenet payment centre","totalAmount":114116.94000000002,"nTransactions":56,"expensesByArea":[{"name":"adult social care","value":52672.94},{"name":"manchester leisure","value":26421.929999999997},{"name":"regeneration finance","value":16100.54},{"name":"chief executives","value":12953.66},{"name":"childrens services","value":5967.87}],"expensesByType":[{"name":"landline telephone charges","value":80885.43000000002},{"name":"landline telephone","value":33231.51}],"lastTransactions":[{"year":2021,"serviceArea":"regeneration finance","expensesType":"landline telephone charges","supplier":"bt featurenet payment centre","amount":1878.21,"month":1,"paymentDate":1611187200000},{"year":2020,"serviceArea":"adult social care","expensesType":"landline telephone charges","supplier":"bt featurenet payment centre","amount":644.71,"month":10,"paymentDate":1603670400000},{"year":2020,"serviceArea":"regeneration finance","expensesType":"landline telephone charges","supplier":"bt featurenet payment centre","amount":671.21,"month":9,"paymentDate":1600992000000},{"year":2020,"serviceArea":"adult social care","expensesType":"landline telephone charges","supplier":"bt featurenet payment centre","amount":645.85,"month":7,"paymentDate":1594684800000},{"year":2020,"serviceArea":"regeneration finance","expensesType":"landline telephone charges","supplier":"bt featurenet payment centre","amount":1977.8,"month":5,"paymentDate":1590019200000}]}