{"supplier":"camps solicitors","totalAmount":7649.68,"nTransactions":2,"expensesByArea":[{"name":"housing revenue account","value":7649.68}],"expensesByType":[{"name":"compensation payments","value":7649.68}],"lastTransactions":[{"year":2013,"serviceArea":"housing revenue account","expensesType":"compensation payments","supplier":"camps solicitors","amount":7000,"month":12,"paymentDate":1385942400000},{"year":2012,"serviceArea":"housing revenue account","expensesType":"compensation payments","supplier":"camps solicitors","amount":649.68,"month":5,"paymentDate":1335830400000}]}