{"supplier":"clearway drainage systems ltd","totalAmount":4029334.1499999994,"nTransactions":533,"expensesByArea":[{"name":"highways services","value":1890530.25},{"name":"hospitality + trading services","value":1150355.7700000005},{"name":"environment and operations","value":515309.7799999999},{"name":"chief executives","value":419190.2},{"name":"manchester leisure","value":48736.21}],"expensesByType":[{"name":"payments to sub-contractors","value":3392646.6499999994},{"name":"construction works","value":189418.67999999996},{"name":"infrastructure - adaptations","value":189295.36000000002},{"name":"infrastructure - construction","value":117168.01000000001},{"name":"camc/not assigned","value":59018.40000000001}],"lastTransactions":[{"year":2021,"serviceArea":"manchester leisure","expensesType":"equipment","supplier":"clearway drainage systems ltd","amount":1349.35,"month":10,"paymentDate":1635465600000},{"year":2021,"serviceArea":"highways services","expensesType":"payments to sub-contractors","supplier":"clearway drainage systems ltd","amount":14500,"month":10,"paymentDate":1635465600000},{"year":2021,"serviceArea":"highways services","expensesType":"payments to sub-contractors","supplier":"clearway drainage systems ltd","amount":9720,"month":10,"paymentDate":1635465600000},{"year":2021,"serviceArea":"highways services","expensesType":"payments to sub-contractors","supplier":"clearway drainage systems ltd","amount":2250,"month":10,"paymentDate":1635465600000},{"year":2021,"serviceArea":"highways services","expensesType":"payments to sub-contractors","supplier":"clearway drainage systems ltd","amount":1620,"month":10,"paymentDate":1635465600000}]}