{"supplier":"cms cameron mckenna","totalAmount":167031.91999999998,"nTransactions":30,"expensesByArea":[{"name":"chief executives","value":167031.92}],"expensesByType":[{"name":"works and associated costs for land and buildings","value":160379.47},{"name":"legal fees","value":6652.45}],"lastTransactions":[{"year":2021,"serviceArea":"chief executives","expensesType":"works and associated costs for land and buildings","supplier":"cms cameron mckenna","amount":1726.55,"month":12,"paymentDate":1639094400000},{"year":2021,"serviceArea":"chief executives","expensesType":"works and associated costs for land and buildings","supplier":"cms cameron mckenna","amount":1857.45,"month":8,"paymentDate":1629676800000},{"year":2021,"serviceArea":"chief executives","expensesType":"works and associated costs for land and buildings","supplier":"cms cameron mckenna","amount":1191.1,"month":8,"paymentDate":1629676800000},{"year":2021,"serviceArea":"chief executives","expensesType":"works and associated costs for land and buildings","supplier":"cms cameron mckenna","amount":993.9,"month":8,"paymentDate":1629676800000},{"year":2021,"serviceArea":"chief executives","expensesType":"works and associated costs for land and buildings","supplier":"cms cameron mckenna","amount":929.83,"month":8,"paymentDate":1629676800000}]}