{"supplier":"college of mediators","totalAmount":6122,"nTransactions":7,"expensesByArea":[{"name":"hospitality + trading services","value":3224},{"name":"environment and operations","value":1778},{"name":"chief executives","value":1120}],"expensesByType":[{"name":"grant and subscriptions awarded","value":3092},{"name":"subsistence and conference expenses","value":1754},{"name":"grant payments","value":649},{"name":"proffesional fees","value":627}],"lastTransactions":[{"year":2017,"serviceArea":"environment and operations","expensesType":"grant payments","supplier":"college of mediators","amount":649,"month":2,"paymentDate":1485993600000},{"year":2015,"serviceArea":"environment and operations","expensesType":"grant and subscriptions awarded","supplier":"college of mediators","amount":602,"month":5,"paymentDate":1431302400000},{"year":2014,"serviceArea":"environment and operations","expensesType":"subsistence and conference expenses","supplier":"college of mediators","amount":527,"month":2,"paymentDate":1392336000000},{"year":2013,"serviceArea":"hospitality + trading services","expensesType":"subsistence and conference expenses","supplier":"college of mediators","amount":1227,"month":2,"paymentDate":1360886400000},{"year":2012,"serviceArea":"hospitality + trading services","expensesType":"proffesional fees","supplier":"college of mediators","amount":627,"month":10,"paymentDate":1350345600000}]}