{"supplier":"computerland uk ltd","totalAmount":7730244.609999997,"nTransactions":761,"expensesByArea":[{"name":"chief executives","value":5492884.81},{"name":"corporate services","value":1849140.4600000002},{"name":"libraries and theatres","value":75566.14},{"name":"childrens services","value":68825.49999999999},{"name":"regeneration finance","value":68019.19999999998}],"expensesByType":[{"name":"i t provision","value":3235924.6799999997},{"name":"licences purchase","value":1314536.4199999997},{"name":"hire of equipment","value":1030294.58},{"name":"vehicle plant furniture and equipment","value":816489.9300000003},{"name":"ict sup & maintnance","value":543129.8}],"lastTransactions":[{"year":2017,"serviceArea":"chief executives","expensesType":"i t provision","supplier":"computerland uk ltd","amount":550,"month":11,"paymentDate":1511827200000},{"year":2017,"serviceArea":"chief executives","expensesType":"licences purchase","supplier":"computerland uk ltd","amount":2976.3,"month":11,"paymentDate":1511136000000},{"year":2017,"serviceArea":"manchester leisure","expensesType":"licences purchase","supplier":"computerland uk ltd","amount":1592.85,"month":5,"paymentDate":1493769600000},{"year":2017,"serviceArea":"manchester leisure","expensesType":"licences purchase","supplier":"computerland uk ltd","amount":1592.85,"month":5,"paymentDate":1493683200000},{"year":2017,"serviceArea":"manchester leisure","expensesType":"licences purchase","supplier":"computerland uk ltd","amount":-1592.85,"month":5,"paymentDate":1493683200000}]}