{"supplier":"elliott group ltd","totalAmount":27854.460000000003,"nTransactions":14,"expensesByArea":[{"name":"hospitality + trading services","value":23737.010000000002},{"name":"chief executives","value":2854.65},{"name":"highways services","value":700},{"name":"corporate services","value":562.8}],"expensesByType":[{"name":"hire of equipment","value":16664.36},{"name":"equipment","value":6852.5},{"name":"hire of machinery","value":3074.7999999999997},{"name":"building materials for direct delivery","value":700},{"name":"car parking permits","value":562.8}],"lastTransactions":[{"year":2021,"serviceArea":"highways services","expensesType":"building materials for direct delivery","supplier":"elliott group ltd","amount":700,"month":1,"paymentDate":1611878400000},{"year":2020,"serviceArea":"corporate services","expensesType":"car parking permits","supplier":"elliott group ltd","amount":562.8,"month":3,"paymentDate":1584316800000},{"year":2013,"serviceArea":"chief executives","expensesType":"hire of equipment","supplier":"elliott group ltd","amount":1250,"month":12,"paymentDate":1388448000000},{"year":2013,"serviceArea":"hospitality + trading services","expensesType":"hire of equipment","supplier":"elliott group ltd","amount":3380.14,"month":3,"paymentDate":1364428800000},{"year":2013,"serviceArea":"hospitality + trading services","expensesType":"hire of machinery","supplier":"elliott group ltd","amount":826.4,"month":3,"paymentDate":1364342400000}]}