{"supplier":"f.r.sharrock ltd","totalAmount":3506644.3599999994,"nTransactions":296,"expensesByArea":[{"name":"hospitality + trading services","value":3476782.359999999},{"name":"manchester leisure","value":28151.17},{"name":"regeneration finance","value":915.83},{"name":"environment and operations","value":795}],"expensesByType":[{"name":"hire of machinery","value":2960555.1300000004},{"name":"machinery and equipment repairs","value":254730.74000000002},{"name":"hire of equipment","value":171621.00000000003},{"name":"vehicle hire costs","value":84329.78},{"name":"vehicle repairs","value":19447.71}],"lastTransactions":[{"year":2021,"serviceArea":"hospitality + trading services","expensesType":"hire of machinery","supplier":"f.r.sharrock ltd","amount":49370.75,"month":2,"paymentDate":1612828800000},{"year":2021,"serviceArea":"manchester leisure","expensesType":"hire of machinery","supplier":"f.r.sharrock ltd","amount":818.34,"month":1,"paymentDate":1610928000000},{"year":2021,"serviceArea":"manchester leisure","expensesType":"hire of machinery","supplier":"f.r.sharrock ltd","amount":782.76,"month":1,"paymentDate":1610928000000},{"year":2021,"serviceArea":"manchester leisure","expensesType":"hire of machinery","supplier":"f.r.sharrock ltd","amount":747.18,"month":1,"paymentDate":1610928000000},{"year":2021,"serviceArea":"manchester leisure","expensesType":"hire of machinery","supplier":"f.r.sharrock ltd","amount":-747.18,"month":1,"paymentDate":1610928000000}]}