{"supplier":"film and video umbrella","totalAmount":11000,"nTransactions":2,"expensesByArea":[{"name":"manchester leisure","value":11000}],"expensesByType":[{"name":"professional fees","value":11000}],"lastTransactions":[{"year":2018,"serviceArea":"manchester leisure","expensesType":"professional fees","supplier":"film and video umbrella","amount":3000,"month":3,"paymentDate":1521417600000},{"year":2017,"serviceArea":"manchester leisure","expensesType":"professional fees","supplier":"film and video umbrella","amount":8000,"month":4,"paymentDate":1492992000000}]}