{"supplier":"garside and  laycock ltd","totalAmount":2077912.6800000002,"nTransactions":61,"expensesByArea":[{"name":"childrens services","value":1056597.6800000002},{"name":"corporate services","value":782336.0099999999},{"name":"chief executives","value":123328.16},{"name":"manchester leisure","value":103113.59},{"name":"housing general fund","value":12537.24}],"expensesByType":[{"name":"works and associated costs for land and buildings","value":1598483.0100000002},{"name":"external repairs and maintenance for buildings","value":262781.27},{"name":"construction works","value":123328.16},{"name":"responsive repairs work","value":43223},{"name":"camc/not assigned","value":37560}],"lastTransactions":[{"year":2014,"serviceArea":"corporate services","expensesType":"works and associated costs for land and buildings","supplier":"garside and  laycock ltd","amount":46719.55,"month":9,"paymentDate":1411689600000},{"year":2014,"serviceArea":"corporate services","expensesType":"works and associated costs for land and buildings","supplier":"garside and  laycock ltd","amount":33479,"month":9,"paymentDate":1411689600000},{"year":2014,"serviceArea":"corporate services","expensesType":"external repairs and maintenance for buildings","supplier":"garside and  laycock ltd","amount":604.68,"month":8,"paymentDate":1409270400000},{"year":2014,"serviceArea":"corporate services","expensesType":"works and associated costs for land and buildings","supplier":"garside and  laycock ltd","amount":23749,"month":7,"paymentDate":1406505600000},{"year":2014,"serviceArea":"corporate services","expensesType":"works and associated costs for land and buildings","supplier":"garside and  laycock ltd","amount":96615.57,"month":7,"paymentDate":1406246400000}]}