{"supplier":"greater manchester mental health","totalAmount":33603289.77000001,"nTransactions":447,"expensesByArea":[{"name":"adult social care","value":33400015.77},{"name":"corporate services","value":203274}],"expensesByType":[{"name":"third party payments to health authority","value":19619522.010000005},{"name":"supporting people payments","value":9223529},{"name":"rents","value":2412638},{"name":"payments for services","value":1562244},{"name":"works and associated costs for land and buildings","value":203274}],"lastTransactions":[{"year":2021,"serviceArea":"adult social care","expensesType":"third party payments to health authority","supplier":"greater manchester mental health","amount":116324,"month":6,"paymentDate":1623283200000},{"year":2021,"serviceArea":"adult social care","expensesType":"third party payments to health authority","supplier":"greater manchester mental health","amount":32916,"month":6,"paymentDate":1623283200000},{"year":2021,"serviceArea":"adult social care","expensesType":"third party payments to health authority","supplier":"greater manchester mental health","amount":11763,"month":6,"paymentDate":1623283200000},{"year":2021,"serviceArea":"adult social care","expensesType":"training and development","supplier":"greater manchester mental health","amount":6977.32,"month":6,"paymentDate":1623196800000},{"year":2021,"serviceArea":"adult social care","expensesType":"training and development","supplier":"greater manchester mental health","amount":6743.11,"month":6,"paymentDate":1623110400000}]}