{"supplier":"herida healthcare plc","totalAmount":18650,"nTransactions":8,"expensesByArea":[{"name":"adult social care","value":18650}],"expensesByType":[{"name":"equipment","value":18650}],"lastTransactions":[{"year":2021,"serviceArea":"adult social care","expensesType":"equipment","supplier":"herida healthcare plc","amount":1100,"month":6,"paymentDate":1623369600000},{"year":2021,"serviceArea":"adult social care","expensesType":"equipment","supplier":"herida healthcare plc","amount":2100,"month":5,"paymentDate":1621987200000},{"year":2021,"serviceArea":"adult social care","expensesType":"equipment","supplier":"herida healthcare plc","amount":3500,"month":5,"paymentDate":1621814400000},{"year":2021,"serviceArea":"adult social care","expensesType":"equipment","supplier":"herida healthcare plc","amount":2100,"month":5,"paymentDate":1620950400000},{"year":2021,"serviceArea":"adult social care","expensesType":"equipment","supplier":"herida healthcare plc","amount":3500,"month":4,"paymentDate":1617926400000}]}