{"supplier":"iss facility services ltd","totalAmount":164589.25,"nTransactions":89,"expensesByArea":[{"name":"manchester leisure","value":164589.25}],"expensesByType":[{"name":"grounds maintenance","value":106128.55},{"name":"grounds maintenance costs","value":52471.25},{"name":"external repairs and maintenance for buildings","value":4397.25},{"name":"building materials for direct delivery","value":1592.2}],"lastTransactions":[{"year":2018,"serviceArea":"manchester leisure","expensesType":"grounds maintenance costs","supplier":"iss facility services ltd","amount":2357.25,"month":4,"paymentDate":1522972800000},{"year":2017,"serviceArea":"manchester leisure","expensesType":"external repairs and maintenance for buildings","supplier":"iss facility services ltd","amount":2357.25,"month":11,"paymentDate":1510704000000},{"year":2017,"serviceArea":"manchester leisure","expensesType":"external repairs and maintenance for buildings","supplier":"iss facility services ltd","amount":2040,"month":11,"paymentDate":1510704000000},{"year":2017,"serviceArea":"manchester leisure","expensesType":"grounds maintenance costs","supplier":"iss facility services ltd","amount":2357.25,"month":11,"paymentDate":1510704000000},{"year":2017,"serviceArea":"manchester leisure","expensesType":"grounds maintenance costs","supplier":"iss facility services ltd","amount":2357.25,"month":10,"paymentDate":1507593600000}]}