{"supplier":"kays medical ltd","totalAmount":1200,"nTransactions":2,"expensesByArea":[{"name":"chief executives","value":1200}],"expensesByType":[{"name":"consumable items eg toilet rolls, soap etc","value":1200}],"lastTransactions":[{"year":2021,"serviceArea":"chief executives","expensesType":"consumable items eg toilet rolls, soap etc","supplier":"kays medical ltd","amount":650,"month":10,"paymentDate":1633651200000},{"year":2021,"serviceArea":"chief executives","expensesType":"consumable items eg toilet rolls, soap etc","supplier":"kays medical ltd","amount":550,"month":10,"paymentDate":1633651200000}]}