{"supplier":"knowsley m.b.c.","totalAmount":114781,"nTransactions":5,"expensesByArea":[{"name":"childrens services","value":114781}],"expensesByType":[{"name":"third party payments to other local authorities","value":114781}],"lastTransactions":[{"year":2013,"serviceArea":"childrens services","expensesType":"third party payments to other local authorities","supplier":"knowsley m.b.c.","amount":21012,"month":5,"paymentDate":1368403200000},{"year":2012,"serviceArea":"childrens services","expensesType":"third party payments to other local authorities","supplier":"knowsley m.b.c.","amount":63036,"month":9,"paymentDate":1348444800000},{"year":2012,"serviceArea":"childrens services","expensesType":"third party payments to other local authorities","supplier":"knowsley m.b.c.","amount":5039,"month":8,"paymentDate":1343952000000},{"year":2011,"serviceArea":"childrens services","expensesType":"third party payments to other local authorities","supplier":"knowsley m.b.c.","amount":4198,"month":9,"paymentDate":1315526400000},{"year":2011,"serviceArea":"childrens services","expensesType":"third party payments to other local authorities","supplier":"knowsley m.b.c.","amount":21496,"month":2,"paymentDate":1297900800000}]}