{"supplier":"m&g transport & technical services","totalAmount":147570.68,"nTransactions":29,"expensesByArea":[{"name":"regeneration finance","value":118454},{"name":"manchester leisure","value":28278.68},{"name":"hospitality + trading services","value":838}],"expensesByType":[{"name":"professional fees","value":108993.36},{"name":"equipment","value":13953.9},{"name":"transport and driver hire","value":11481.42},{"name":"removal and storage of furniture","value":7864},{"name":"compensation payments","value":3000}],"lastTransactions":[{"year":2021,"serviceArea":"manchester leisure","expensesType":"transport and driver hire","supplier":"m&g transport & technical services","amount":898,"month":8,"paymentDate":1630368000000},{"year":2021,"serviceArea":"regeneration finance","expensesType":"removal and storage of furniture","supplier":"m&g transport & technical services","amount":848,"month":8,"paymentDate":1630022400000},{"year":2021,"serviceArea":"manchester leisure","expensesType":"transport and driver hire","supplier":"m&g transport & technical services","amount":680,"month":8,"paymentDate":1628208000000},{"year":2021,"serviceArea":"manchester leisure","expensesType":"professional fees","supplier":"m&g transport & technical services","amount":645,"month":3,"paymentDate":1616112000000},{"year":2021,"serviceArea":"manchester leisure","expensesType":"transport and driver hire","supplier":"m&g transport & technical services","amount":785,"month":3,"paymentDate":1616025600000}]}