{"supplier":"manchester & cheshire construction","totalAmount":1595645.2200000002,"nTransactions":84,"expensesByArea":[{"name":"childrens services","value":750047.54},{"name":"corporate services","value":459349.62},{"name":"manchester leisure","value":196246.03},{"name":"highways services","value":96788.75},{"name":"hospitality + trading services","value":37458.66}],"expensesByType":[{"name":"works and associated costs for land and buildings","value":1139287.1899999995},{"name":"external repairs and maintenance for buildings","value":240109},{"name":"payments to sub-contractors","value":78623.21},{"name":"grounds maintenance costs","value":48235},{"name":"grounds maintenance","value":21747}],"lastTransactions":[{"year":2020,"serviceArea":"highways services","expensesType":"payments to sub-contractors","supplier":"manchester & cheshire construction","amount":545,"month":6,"paymentDate":1591574400000},{"year":2020,"serviceArea":"highways services","expensesType":"professional fees","supplier":"manchester & cheshire construction","amount":16607.25,"month":4,"paymentDate":1586390400000},{"year":2020,"serviceArea":"highways services","expensesType":"professional fees","supplier":"manchester & cheshire construction","amount":2741.5,"month":2,"paymentDate":1581465600000},{"year":2020,"serviceArea":"highways services","expensesType":"professional fees","supplier":"manchester & cheshire construction","amount":1465,"month":2,"paymentDate":1581465600000},{"year":2019,"serviceArea":"highways services","expensesType":"grounds maintenance costs","supplier":"manchester & cheshire construction","amount":878,"month":12,"paymentDate":1577145600000}]}