{"supplier":"manchester & district housing assoc","totalAmount":154496.48000000007,"nTransactions":143,"expensesByArea":[{"name":"adult social care","value":154496.48}],"expensesByType":[{"name":"supporting people payments","value":110218.74},{"name":"third party payments relating to voluntary organisations","value":44277.73999999999}],"lastTransactions":[{"year":2017,"serviceArea":"adult social care","expensesType":"third party payments relating to voluntary organisations","supplier":"manchester & district housing assoc","amount":1003.81,"month":7,"paymentDate":1500422400000},{"year":2017,"serviceArea":"adult social care","expensesType":"third party payments relating to voluntary organisations","supplier":"manchester & district housing assoc","amount":1003.51,"month":7,"paymentDate":1500422400000},{"year":2017,"serviceArea":"adult social care","expensesType":"third party payments relating to voluntary organisations","supplier":"manchester & district housing assoc","amount":760.13,"month":7,"paymentDate":1500422400000},{"year":2017,"serviceArea":"adult social care","expensesType":"third party payments relating to voluntary organisations","supplier":"manchester & district housing assoc","amount":1003.81,"month":6,"paymentDate":1498176000000},{"year":2017,"serviceArea":"adult social care","expensesType":"third party payments relating to voluntary organisations","supplier":"manchester & district housing assoc","amount":1003.51,"month":6,"paymentDate":1498176000000}]}