{"supplier":"northmoor together","totalAmount":13177.670000000002,"nTransactions":7,"expensesByArea":[{"name":"manchester leisure","value":13177.67}],"expensesByType":[{"name":"grant and subscriptions awarded","value":10177.67},{"name":"grant payments","value":3000}],"lastTransactions":[{"year":2021,"serviceArea":"manchester leisure","expensesType":"grant and subscriptions awarded","supplier":"northmoor together","amount":1542.97,"month":12,"paymentDate":1640217600000},{"year":2021,"serviceArea":"manchester leisure","expensesType":"grant and subscriptions awarded","supplier":"northmoor together","amount":2020,"month":10,"paymentDate":1633392000000},{"year":2021,"serviceArea":"manchester leisure","expensesType":"grant and subscriptions awarded","supplier":"northmoor together","amount":1000,"month":7,"paymentDate":1627516800000},{"year":2021,"serviceArea":"manchester leisure","expensesType":"grant and subscriptions awarded","supplier":"northmoor together","amount":2800,"month":7,"paymentDate":1626652800000},{"year":2020,"serviceArea":"manchester leisure","expensesType":"grant and subscriptions awarded","supplier":"northmoor together","amount":1209.7,"month":9,"paymentDate":1599177600000}]}