{"supplier":"oakhill publishing ltd","totalAmount":42283.340000000004,"nTransactions":15,"expensesByArea":[{"name":"manchester leisure","value":29955.070000000003},{"name":"libraries and theatres","value":12328.269999999999}],"expensesByType":[{"name":"library materials acquisition","value":42283.34}],"lastTransactions":[{"year":2017,"serviceArea":"manchester leisure","expensesType":"library materials acquisition","supplier":"oakhill publishing ltd","amount":5691.6,"month":3,"paymentDate":1489708800000},{"year":2017,"serviceArea":"manchester leisure","expensesType":"library materials acquisition","supplier":"oakhill publishing ltd","amount":1020,"month":3,"paymentDate":1489708800000},{"year":2016,"serviceArea":"manchester leisure","expensesType":"library materials acquisition","supplier":"oakhill publishing ltd","amount":6829.92,"month":3,"paymentDate":1457913600000},{"year":2016,"serviceArea":"manchester leisure","expensesType":"library materials acquisition","supplier":"oakhill publishing ltd","amount":1224,"month":3,"paymentDate":1457913600000},{"year":2015,"serviceArea":"manchester leisure","expensesType":"library materials acquisition","supplier":"oakhill publishing ltd","amount":5691.6,"month":2,"paymentDate":1424649600000}]}