{"supplier":"one green world","totalAmount":37880.28,"nTransactions":26,"expensesByArea":[{"name":"manchester leisure","value":36880.28},{"name":"environment and operations","value":1000}],"expensesByType":[{"name":"payments to sub-contractors","value":21774.190000000002},{"name":"equipment","value":6750},{"name":"training and development","value":3200},{"name":"sub contractors","value":2680},{"name":"building materials for direct delivery","value":2206.09}],"lastTransactions":[{"year":2020,"serviceArea":"manchester leisure","expensesType":"grant payments","supplier":"one green world","amount":700,"month":10,"paymentDate":1603929600000},{"year":2020,"serviceArea":"manchester leisure","expensesType":"equipment","supplier":"one green world","amount":800,"month":3,"paymentDate":1584489600000},{"year":2020,"serviceArea":"manchester leisure","expensesType":"equipment","supplier":"one green world","amount":500,"month":2,"paymentDate":1581897600000},{"year":2020,"serviceArea":"manchester leisure","expensesType":"payments to sub-contractors","supplier":"one green world","amount":500,"month":2,"paymentDate":1581897600000},{"year":2020,"serviceArea":"manchester leisure","expensesType":"payments to sub-contractors","supplier":"one green world","amount":1350,"month":2,"paymentDate":1581292800000}]}