{"supplier":"perform better ltd","totalAmount":97277,"nTransactions":5,"expensesByArea":[{"name":"chief executives","value":97277}],"expensesByType":[{"name":"building works","value":97277}],"lastTransactions":[{"year":2016,"serviceArea":"chief executives","expensesType":"building works","supplier":"perform better ltd","amount":2870,"month":3,"paymentDate":1459382400000},{"year":2016,"serviceArea":"chief executives","expensesType":"building works","supplier":"perform better ltd","amount":-1435,"month":3,"paymentDate":1459382400000},{"year":2016,"serviceArea":"chief executives","expensesType":"building works","supplier":"perform better ltd","amount":1992,"month":1,"paymentDate":1453075200000},{"year":2016,"serviceArea":"chief executives","expensesType":"building works","supplier":"perform better ltd","amount":90850,"month":1,"paymentDate":1452124800000},{"year":2016,"serviceArea":"chief executives","expensesType":"building works","supplier":"perform better ltd","amount":3000,"month":1,"paymentDate":1452124800000}]}