{"supplier":"peters bookselling services","totalAmount":219151.77000000002,"nTransactions":213,"expensesByArea":[{"name":"manchester leisure","value":219151.76999999984}],"expensesByType":[{"name":"library materials acquisition","value":214775.77999999985},{"name":"reference materials","value":4375.99}],"lastTransactions":[{"year":2021,"serviceArea":"manchester leisure","expensesType":"library materials acquisition","supplier":"peters bookselling services","amount":908.5,"month":2,"paymentDate":1614211200000},{"year":2021,"serviceArea":"manchester leisure","expensesType":"library materials acquisition","supplier":"peters bookselling services","amount":561.99,"month":2,"paymentDate":1614211200000},{"year":2021,"serviceArea":"manchester leisure","expensesType":"library materials acquisition","supplier":"peters bookselling services","amount":2051.31,"month":2,"paymentDate":1613606400000},{"year":2021,"serviceArea":"manchester leisure","expensesType":"library materials acquisition","supplier":"peters bookselling services","amount":1742.57,"month":2,"paymentDate":1613606400000},{"year":2021,"serviceArea":"manchester leisure","expensesType":"library materials acquisition","supplier":"peters bookselling services","amount":1557.34,"month":2,"paymentDate":1613606400000}]}