{"supplier":"premier paper group ltd","totalAmount":462029.5600000004,"nTransactions":254,"expensesByArea":[{"name":"chief executives","value":462029.5600000001}],"expensesByType":[{"name":"paper & envelopes","value":417669.64000000013},{"name":"printing","value":23648.899999999998},{"name":"camc/not assigned","value":16800},{"name":"stationery","value":3278.22},{"name":"advertising","value":632.8}],"lastTransactions":[{"year":2020,"serviceArea":"chief executives","expensesType":"paper & envelopes","supplier":"premier paper group ltd","amount":1684.98,"month":12,"paymentDate":1606780800000},{"year":2020,"serviceArea":"chief executives","expensesType":"paper & envelopes","supplier":"premier paper group ltd","amount":1954.22,"month":11,"paymentDate":1605744000000},{"year":2020,"serviceArea":"chief executives","expensesType":"paper & envelopes","supplier":"premier paper group ltd","amount":-1954.22,"month":11,"paymentDate":1605744000000},{"year":2020,"serviceArea":"chief executives","expensesType":"paper & envelopes","supplier":"premier paper group ltd","amount":886.27,"month":10,"paymentDate":1602028800000},{"year":2020,"serviceArea":"chief executives","expensesType":"paper & envelopes","supplier":"premier paper group ltd","amount":1954.22,"month":9,"paymentDate":1601424000000}]}