{"supplier":"psg law ltd","totalAmount":10000,"nTransactions":3,"expensesByArea":[{"name":"insurance fund","value":8440.630000000001},{"name":"regeneration finance","value":1559.37}],"expensesByType":[{"name":"insurance","value":8440.630000000001},{"name":"compensation payments","value":1559.37}],"lastTransactions":[{"year":2018,"serviceArea":"insurance fund","expensesType":"insurance","supplier":"psg law ltd","amount":5000,"month":4,"paymentDate":1523404800000},{"year":2017,"serviceArea":"regeneration finance","expensesType":"compensation payments","supplier":"psg law ltd","amount":1559.37,"month":11,"paymentDate":1512000000000},{"year":2017,"serviceArea":"insurance fund","expensesType":"insurance","supplier":"psg law ltd","amount":3440.63,"month":11,"paymentDate":1512000000000}]}