{"supplier":"savas & savage solicitors ltd","totalAmount":32778.44,"nTransactions":6,"expensesByArea":[{"name":"insurance fund","value":12941.94},{"name":"environment and operations","value":9760},{"name":"manchester leisure","value":5638},{"name":"highways services","value":4438.5}],"expensesByType":[{"name":"compensation payments","value":19836.5},{"name":"insurance","value":12941.94}],"lastTransactions":[{"year":2019,"serviceArea":"highways services","expensesType":"compensation payments","supplier":"savas & savage solicitors ltd","amount":2188.5,"month":3,"paymentDate":1551744000000},{"year":2019,"serviceArea":"highways services","expensesType":"compensation payments","supplier":"savas & savage solicitors ltd","amount":2250,"month":2,"paymentDate":1550534400000},{"year":2015,"serviceArea":"manchester leisure","expensesType":"compensation payments","supplier":"savas & savage solicitors ltd","amount":5638,"month":12,"paymentDate":1450828800000},{"year":2014,"serviceArea":"insurance fund","expensesType":"insurance","supplier":"savas & savage solicitors ltd","amount":11951.94,"month":11,"paymentDate":1416528000000},{"year":2014,"serviceArea":"insurance fund","expensesType":"insurance","supplier":"savas & savage solicitors ltd","amount":990,"month":8,"paymentDate":1409270400000}]}