{"supplier":"stonewall equality ltd","totalAmount":6500,"nTransactions":4,"expensesByArea":[{"name":"chief executives","value":6500}],"expensesByType":[{"name":"grant and subscriptions awarded","value":4750},{"name":"camc/not assigned","value":1750}],"lastTransactions":[{"year":2014,"serviceArea":"chief executives","expensesType":"grant and subscriptions awarded","supplier":"stonewall equality ltd","amount":1750,"month":5,"paymentDate":1398902400000},{"year":2013,"serviceArea":"chief executives","expensesType":"camc/not assigned","supplier":"stonewall equality ltd","amount":1750,"month":5,"paymentDate":1367884800000},{"year":2012,"serviceArea":"chief executives","expensesType":"grant and subscriptions awarded","supplier":"stonewall equality ltd","amount":1500,"month":5,"paymentDate":1336435200000},{"year":2011,"serviceArea":"chief executives","expensesType":"grant and subscriptions awarded","supplier":"stonewall equality ltd","amount":1500,"month":8,"paymentDate":1314316800000}]}