{"supplier":"stripes solicitors","totalAmount":4000,"nTransactions":2,"expensesByArea":[{"name":"highways services","value":4000}],"expensesByType":[{"name":"compensation payments","value":4000}],"lastTransactions":[{"year":2011,"serviceArea":"highways services","expensesType":"compensation payments","supplier":"stripes solicitors","amount":2000,"month":8,"paymentDate":1314748800000},{"year":2011,"serviceArea":"highways services","expensesType":"compensation payments","supplier":"stripes solicitors","amount":2000,"month":6,"paymentDate":1309305600000}]}