{"supplier":"tadtu distribution ltd","totalAmount":10488,"nTransactions":10,"expensesByArea":[{"name":"manchester leisure","value":6178},{"name":"chief executives","value":3810},{"name":"highways services","value":500}],"expensesByType":[{"name":"courier costs","value":6178},{"name":"printing","value":3810},{"name":"postage","value":500}],"lastTransactions":[{"year":2021,"serviceArea":"manchester leisure","expensesType":"courier costs","supplier":"tadtu distribution ltd","amount":1200,"month":8,"paymentDate":1627948800000},{"year":2021,"serviceArea":"chief executives","expensesType":"printing","supplier":"tadtu distribution ltd","amount":500,"month":2,"paymentDate":1614297600000},{"year":2021,"serviceArea":"chief executives","expensesType":"printing","supplier":"tadtu distribution ltd","amount":2000,"month":2,"paymentDate":1612742400000},{"year":2020,"serviceArea":"chief executives","expensesType":"printing","supplier":"tadtu distribution ltd","amount":500,"month":9,"paymentDate":1599523200000},{"year":2020,"serviceArea":"highways services","expensesType":"postage","supplier":"tadtu distribution ltd","amount":500,"month":8,"paymentDate":1598227200000}]}