{"supplier":"target psychology ltd","totalAmount":94287.46,"nTransactions":71,"expensesByArea":[{"name":"chief executives","value":44224.969999999994},{"name":"adult social care","value":28274.420000000002},{"name":"childrens & education services","value":21788.07}],"expensesByType":[{"name":"professional fees","value":65135.27999999999},{"name":"compensation payments","value":29152.179999999997}],"lastTransactions":[{"year":2021,"serviceArea":"chief executives","expensesType":"professional fees","supplier":"target psychology ltd","amount":912,"month":6,"paymentDate":1623024000000},{"year":2021,"serviceArea":"childrens & education services","expensesType":"professional fees","supplier":"target psychology ltd","amount":2340,"month":5,"paymentDate":1622073600000},{"year":2021,"serviceArea":"chief executives","expensesType":"professional fees","supplier":"target psychology ltd","amount":6322.1,"month":5,"paymentDate":1620777600000},{"year":2021,"serviceArea":"chief executives","expensesType":"compensation payments","supplier":"target psychology ltd","amount":1096.5,"month":4,"paymentDate":1619395200000},{"year":2021,"serviceArea":"childrens & education services","expensesType":"professional fees","supplier":"target psychology ltd","amount":904.8,"month":4,"paymentDate":1617840000000}]}