{"supplier":"the printroom uk ltd","totalAmount":3900,"nTransactions":4,"expensesByArea":[{"name":"chief executives","value":3900}],"expensesByType":[{"name":"printing","value":3900}],"lastTransactions":[{"year":2017,"serviceArea":"chief executives","expensesType":"printing","supplier":"the printroom uk ltd","amount":520,"month":6,"paymentDate":1496966400000},{"year":2017,"serviceArea":"chief executives","expensesType":"printing","supplier":"the printroom uk ltd","amount":1917,"month":2,"paymentDate":1487116800000},{"year":2016,"serviceArea":"chief executives","expensesType":"printing","supplier":"the printroom uk ltd","amount":751,"month":8,"paymentDate":1472601600000},{"year":2016,"serviceArea":"chief executives","expensesType":"printing","supplier":"the printroom uk ltd","amount":712,"month":8,"paymentDate":1470873600000}]}