{"supplier":"thompsons academy ltd","totalAmount":119968.99,"nTransactions":30,"expensesByArea":[{"name":"childrens & education services","value":106468.99},{"name":"adult social care","value":13500}],"expensesByType":[{"name":"payments for services","value":112618.99},{"name":"other establishments third party payments","value":4500},{"name":"home care payments","value":1950},{"name":"professional fees","value":900}],"lastTransactions":[{"year":2021,"serviceArea":"childrens & education services","expensesType":"payments for services","supplier":"thompsons academy ltd","amount":600,"month":3,"paymentDate":1615939200000},{"year":2021,"serviceArea":"childrens & education services","expensesType":"payments for services","supplier":"thompsons academy ltd","amount":8333,"month":2,"paymentDate":1612396800000},{"year":2021,"serviceArea":"childrens & education services","expensesType":"payments for services","supplier":"thompsons academy ltd","amount":8333,"month":2,"paymentDate":1612396800000},{"year":2021,"serviceArea":"childrens & education services","expensesType":"payments for services","supplier":"thompsons academy ltd","amount":8333,"month":2,"paymentDate":1612396800000},{"year":2021,"serviceArea":"childrens & education services","expensesType":"payments for services","supplier":"thompsons academy ltd","amount":7200,"month":2,"paymentDate":1612396800000}]}