{"supplier":"tiddlywinks day nursery ltd","totalAmount":81384.03000000001,"nTransactions":36,"expensesByArea":[{"name":"adult social care","value":59067.95},{"name":"childrens & education services","value":17370},{"name":"childrens services","value":4946.08}],"expensesByType":[{"name":"contract cleaning external","value":68805},{"name":"rates","value":5089.04},{"name":"rents","value":2723.5},{"name":"day care payments","value":1295},{"name":"building works","value":1244.49}],"lastTransactions":[{"year":2021,"serviceArea":"childrens & education services","expensesType":"day care payments","supplier":"tiddlywinks day nursery ltd","amount":551,"month":5,"paymentDate":1621814400000},{"year":2021,"serviceArea":"childrens & education services","expensesType":"day care payments","supplier":"tiddlywinks day nursery ltd","amount":744,"month":4,"paymentDate":1617667200000},{"year":2021,"serviceArea":"childrens & education services","expensesType":"childminding fee payments","supplier":"tiddlywinks day nursery ltd","amount":775,"month":3,"paymentDate":1615939200000},{"year":2021,"serviceArea":"childrens & education services","expensesType":"contract cleaning external","supplier":"tiddlywinks day nursery ltd","amount":3685.5,"month":3,"paymentDate":1614816000000},{"year":2020,"serviceArea":"childrens & education services","expensesType":"contract cleaning external","supplier":"tiddlywinks day nursery ltd","amount":3627,"month":10,"paymentDate":1603929600000}]}