{"supplier":"tinsdill solicitors","totalAmount":17540,"nTransactions":4,"expensesByArea":[{"name":"highways services","value":17540}],"expensesByType":[{"name":"compensation payments","value":12311.5},{"name":"legal fees","value":5228.5}],"lastTransactions":[{"year":2020,"serviceArea":"highways services","expensesType":"compensation payments","supplier":"tinsdill solicitors","amount":2650,"month":8,"paymentDate":1597968000000},{"year":2020,"serviceArea":"highways services","expensesType":"compensation payments","supplier":"tinsdill solicitors","amount":4411.5,"month":8,"paymentDate":1597968000000},{"year":2017,"serviceArea":"highways services","expensesType":"compensation payments","supplier":"tinsdill solicitors","amount":5250,"month":3,"paymentDate":1489708800000},{"year":2017,"serviceArea":"highways services","expensesType":"legal fees","supplier":"tinsdill solicitors","amount":5228.5,"month":3,"paymentDate":1488412800000}]}