{"supplier":"trident crisis solutions ltd","totalAmount":4973.2,"nTransactions":4,"expensesByArea":[{"name":"libraries and theatres","value":4200},{"name":"manchester leisure","value":773.2}],"expensesByType":[{"name":"training and development","value":3173.2},{"name":"subsistence and conference expenses","value":1800}],"lastTransactions":[{"year":2016,"serviceArea":"manchester leisure","expensesType":"training and development","supplier":"trident crisis solutions ltd","amount":773.2,"month":6,"paymentDate":1464825600000},{"year":2014,"serviceArea":"libraries and theatres","expensesType":"training and development","supplier":"trident crisis solutions ltd","amount":1800,"month":2,"paymentDate":1391558400000},{"year":2014,"serviceArea":"libraries and theatres","expensesType":"training and development","supplier":"trident crisis solutions ltd","amount":600,"month":2,"paymentDate":1391558400000},{"year":2013,"serviceArea":"libraries and theatres","expensesType":"subsistence and conference expenses","supplier":"trident crisis solutions ltd","amount":1800,"month":8,"paymentDate":1375747200000}]}