{"supplier":"winners contract hire ltd","totalAmount":9281912.979999995,"nTransactions":301,"expensesByArea":[{"name":"hospitality + trading services","value":9259916.979999997},{"name":"chief executives","value":21996}],"expensesByType":[{"name":"vehicle hire costs","value":8697008.43},{"name":"vehicle repairs","value":311496.75999999995},{"name":"recharge of veh hire","value":200000},{"name":"payments for services","value":21996},{"name":"camc/not assigned","value":14464.66}],"lastTransactions":[{"year":2021,"serviceArea":"hospitality + trading services","expensesType":"vehicle hire costs","supplier":"winners contract hire ltd","amount":66734.07,"month":12,"paymentDate":1640304000000},{"year":2021,"serviceArea":"hospitality + trading services","expensesType":"vehicle hire costs","supplier":"winners contract hire ltd","amount":74638.74,"month":12,"paymentDate":1638748800000},{"year":2021,"serviceArea":"hospitality + trading services","expensesType":"vehicle hire costs","supplier":"winners contract hire ltd","amount":2250.97,"month":12,"paymentDate":1638489600000},{"year":2021,"serviceArea":"hospitality + trading services","expensesType":"vehicle hire costs","supplier":"winners contract hire ltd","amount":1370.98,"month":12,"paymentDate":1638489600000},{"year":2021,"serviceArea":"hospitality + trading services","expensesType":"vehicle hire costs","supplier":"winners contract hire ltd","amount":69308.97,"month":11,"paymentDate":1635984000000}]}